{
	"_comment":
"#=============================================================
#    DROPS parameter file for twophasedrops
#    simulation of two-phase flow:
#    butanol droplet in water
#=============================================================
# time stepping",

	"Time":
	{
		"NumSteps":		10,
		"StepSize":		0.003,
		"Scheme":		1
	},

	"Stokes":
	{
		"_comment":
"# flow solver",

		"StokesMethod":		20401,
		"InnerIter":		1000,
		"OuterIter":		200,
		"InnerTol":		0.6,
		"OuterTol":		1e-10,
		"PcAIter":		500,
		"PcATol":		0.01,
		"PcSTol":		0.01,
		"XFEMStab":		0.1,
		"Theta":		1
	},

	"NavStokes":
	{
		"Nonlinear":		1,
		"Tol":		1e-10,
		"Iter":		20,
		"Reduction":		0.1
	},

	"Levelset":
	{
		"_comment":
"# levelset solver",

		"Tol":		1e-10,
		"Iter":		1000,
		"SD":		0.1,
		"CurvDiff":		-1,
		"VolCorrection":		1,
		"Theta":		1
	},

	"Coupling":
	{
		"Tol":		1e-10,
		"Iter":		10,
		"Stab":		1,
		"Projection":		0
	},

	"Reparam":
	{
		"_comment":
"# re-initialization of levelset function",

		"Freq":		1,
		"Method":		3,
		"MinGrad":		0.1,
		"MaxGrad":		10,
		"NarrowBand":		-1
	},

	"AdaptRef":
	{
		"_comment":
"# adaptive refinement",

		"Freq":		1,
		"FinestLevel":		3,
		"CoarsestLevel":		0,
		"Width":		0.0004,
		"LoadBalStrategy":		1,
		"Partitioner":		1
	},

	"Mat":
	{
		"_comment":
"# material data, all units are SI",

		"DensDrop":		845.442,
		"ViscDrop":		0.003281,
		"DensFluid":		986.506,
		"ViscFluid":		0.001388,
		"SmoothZone":		0.0001
	},

	"Exp":
	{
		"_comment":
"# experimental conditions",

		"RadDrop":		[2.0e-3, 2.0e-3, 2.0e-3 ],
		"PosDrop":		[6.0e-3, 3.0e-3, 6.0e-3 ],
		"Gravity":		[0, -9.81, 0 ],
		"FlowDir":		1,
		"InflowVel":		0,
		"RadInlet":		0.005,
		"InflowFreq":		0,
		"InflowAmpl":		0
	},

	"SurfTens":
	{
		"_comment":
"# surface tension",

		"VarTension":		0,
		"SurfTension":		0.00163,
		"JumpWidth":		0.0005,
		"RelPos":		1.5,
		"DirtFactor":		0.8
	},

	"Transp":
	{
		"_comment":
"# mass transport",

		"DoTransp":		0,
		"Theta":		0.5,
		"Iter":		200,
		"Tol":		1e-10,
		"DiffPos":		0.005,
		"DiffNeg":		0.01,
		"HPos":		1,
		"HNeg":		0.5,
		"IniCPos":		0.1,
		"IniCNeg":		5,
		"NitschePenalty":		0,
		"NitscheXFEMStab":		0.1
	},

	"SurfTransp":
	{
		"_comment":
"# surfactant transport",

		"DoTransp":		0,
		"Theta":		0.5,
		"Iter":		1000,
		"Tol":		1e-10,
		"OmitBound":		-1,
		"Visc":		1e-05
	},

	"Ensight":
	{
		"_comment":
"# Ensight settings",

		"EnsightOut":		0,
		"EnsCase":		"brick",
		"EnsDir":		"ensight",
		"Binary":		0,
		"MasterOut":		1,
		"GeomName":		"Brick"
	},

	"VTK":
	{
		"_comment":
"#VTK output",

		"VTKOut":		1,
		"VTKDir":		"vtk",
		"VTKName":		"brick",
		"Binary":		1
	},

	"Restart":
	{
		"_comment":
"# Write out results, read in for restart",

		"Serialization":		0,
		"Overwrite":		0,
		"Inputfile":		"none",
		"Outputfile":		"mg",
		"Binary":		0
	},

	"DomainCond":
	{
		"_comment":
"# domain, bnd/ini conditions",

		"InitialCond":		0,
		"GeomType":		1,
		"InitialFile":		"mg/brick",
		"MeshFile":		"12e-3x30e-3x12e-3@4x10x4",
		"BoundaryType":		"0!0!23!2!0!0",
		"BoundaryFncs":		"ZeroVel!ZeroVel!ZeroVel!InflowBrick!ZeroVel!ZeroVel"
	}

}